build/lib/regression_graph/__init__.py
build/lib/regression_graph/regression_graph.py
regression_graph/__init__.py
regression_graph/regression_graph.py
regression_graph-2.dist-info/LICENSE
regression_graph-2.dist-info/METADATA
regression_graph-2.dist-info/WHEEL
regression_graph-2.dist-info/top_level.txt
regression_graph-2.dist-info/RECORD
