Metadata-Version: 2.1
Name: regression-graph
Version: 2
Summary: Python library for regression graphs using coefficents, confidence intervals and p-values
Author: Saema Khanom
License: MIT
Classifier: Programming Language :: Python :: 3
Classifier: License :: OSI Approved :: MIT License
Classifier: Operating System :: OS Independent
License-File: LICENSE
Requires-Dist: numpy
Requires-Dist: matplotlib
Requires-Dist: statsmodels
Requires-Dist: pandas
